ai_safeguards/__init__.py
ai_safeguards/safeguards.py
ai_safeguards/agents/__init__.py
ai_safeguards/agents/agents_settings.py
ai_safeguards/agents/gpt_agent.py
ai_safeguards/embedders/__init__.py
ai_safeguards/embedders/embedders.py
ai_safeguards/prompts/__init__.py
ai_safeguards/prompts/claim_extraction.py
ai_safeguards/prompts/factuality_evaluator.py
ai_safeguards-0.0.6.dist-info/licenses/LICENSE
ai_safeguards-0.0.6.dist-info/METADATA
ai_safeguards-0.0.6.dist-info/WHEEL
ai_safeguards-0.0.6.dist-info/top_level.txt
ai_safeguards-0.0.6.dist-info/RECORD
